asmscan/__init__.py
asmscan/bilstm/__init__.py
asmscan/bilstm/model.py
asmscan/bilstm/resources/tokenizer.pickle
asmscan/bilstm/resources/model/architecture.txt
asmscan/bilstm/resources/model/config.json
asmscan/bilstm/resources/model/cvms/bass-model1.h5
asmscan/bilstm/resources/model/cvms/bass-model2.h5
asmscan/bilstm/resources/model/cvms/bass-model3.h5
asmscan/bilstm/resources/model/cvms/bass-model4.h5
asmscan/bilstm/resources/model/cvms/bass-model5.h5
asmscan/bilstm/resources/model/cvms/bass-model6.h5
asmscan_bilstm-1.0.0.dist-info/LICENSE
asmscan_bilstm-1.0.0.dist-info/METADATA
asmscan_bilstm-1.0.0.dist-info/WHEEL
asmscan_bilstm-1.0.0.dist-info/top_level.txt
asmscan_bilstm-1.0.0.dist-info/RECORD
