Metadata-Version: 2.1
Name: asmscan-bilstm
Version: 1.0.0
Summary: Bidirectional LSTM model for detection of amyloid signaling motifs.
Home-page: https://github.com/jakub-galazka/asmscan-bilstm
Author: Jakub Gałązka
Author-email: kubagalv2@gmail.com
License: GNU General Public License v3 (GPLv3)
Keywords: bidirectional lstm,amyloid signaling motifs
Classifier: Development Status :: 5 - Production/Stable
Classifier: Topic :: Scientific/Engineering :: Bio-Informatics
Classifier: Intended Audience :: Science/Research
Classifier: License :: OSI Approved :: GNU General Public License v3 (GPLv3)
Classifier: Operating System :: OS Independent
Classifier: Programming Language :: Python :: 3.9
Classifier: Programming Language :: Python :: 3.10
Classifier: Programming Language :: Python :: 3.11
Requires-Python: <3.12,>=3.9
License-File: LICENSE
Requires-Dist: tensorflow==2.14.1
Requires-Dist: progress==1.6
